selenium_toolkit/__init__.py
selenium_toolkit/selenium_toolkit.py
selenium_toolkit/utils.py
selenium_toolkit-0.0.9.dist-info/LICENSE
selenium_toolkit-0.0.9.dist-info/METADATA
selenium_toolkit-0.0.9.dist-info/WHEEL
selenium_toolkit-0.0.9.dist-info/RECORD
