Metadata-Version: 2.1
Name: selenium-toolkit
Version: 0.0.9
Summary: this is not a awesome description
Home-page: https://github.com/jorgepvasconcelos/webdriver-toolkit
License: MIT
Keywords: selenium,webdriver
Author: Jorge Vasconcelos
Author-email: john@example.com
Requires-Python: >=3.9,<4.0
Classifier: License :: OSI Approved :: MIT License
Classifier: Programming Language :: Python :: 3
Classifier: Programming Language :: Python :: 3.9
Classifier: Programming Language :: Python :: 3.10
Classifier: Programming Language :: Python :: 3.11
Classifier: Programming Language :: Python :: 3.12
Classifier: Programming Language :: Python :: 3.13
Requires-Dist: selenium (==4.25.0)
Project-URL: Repository, https://github.com/jorgepvasconcelos/webdriver-toolkit
